README.md
setup.py
fcredis/__init__.py
fcredis/base.py
fcredis/tag.py
fcredis/users.py
fcredis.egg-info/PKG-INFO
fcredis.egg-info/SOURCES.txt
fcredis.egg-info/dependency_links.txt
fcredis.egg-info/not-zip-safe
fcredis.egg-info/requires.txt
fcredis.egg-info/top_level.txt
tests/__init__.py
tests/test_tag.py
tests/test_users.py