Metadata-Version: 2.1
Name: fcredis
Version: 0.0.2
Summary: Redis API for users and allocation
Home-page: https://github.com/forever-am/fcredis
Author: Alice Wang
Author-email: alice.wang@forever-am.com
License: GPLv3
Keywords: database,redis
Platform: UNKNOWN
Classifier: Intended Audience :: Developers
Classifier: License :: OSI Approved :: GNU General Public License v3 (GPLv3)
Classifier: Programming Language :: Python :: 3.5
Classifier: Programming Language :: Python :: 3.6
Classifier: Topic :: Software Development :: Libraries
Classifier: Topic :: Software Development :: Libraries :: Python Modules
Provides-Extra: test
